volttron_test_website/main.py
volttron_website-0.1.1a4.dist-info/METADATA
volttron_website-0.1.1a4.dist-info/WHEEL
volttron_website-0.1.1a4.dist-info/RECORD
